clicodelog/__init__.py
clicodelog/__main__.py
clicodelog/app.py
clicodelog/cli.py
clicodelog/templates/index.html
clicodelog-0.1.0.dist-info/licenses/LICENSE
clicodelog-0.1.0.dist-info/METADATA
clicodelog-0.1.0.dist-info/WHEEL
clicodelog-0.1.0.dist-info/entry_points.txt
clicodelog-0.1.0.dist-info/top_level.txt
clicodelog-0.1.0.dist-info/RECORD
