Metadata-Version: 2.4
Name: clicodelog
Version: 0.1.0
Summary: A lightweight, local-first web app to browse, inspect, and export logs from CLI-based AI coding agents
Author: monk1337
License-Expression: MIT
Project-URL: Homepage, https://github.com/monk1337/clicodelog
Project-URL: Repository, https://github.com/monk1337/clicodelog
Project-URL: Issues, https://github.com/monk1337/clicodelog/issues
Keywords: claude,claude-code,openai,codex,gemini,gemini-cli,ai,log,viewer,cli
Classifier: Development Status :: 4 - Beta
Classifier: Environment :: Web Environment
Classifier: Framework :: Flask
Classifier: Intended Audience :: Developers
Classifier: Operating System :: OS Independent
Classifier: Programming Language :: Python :: 3
Classifier: Programming Language :: Python :: 3.7
Classifier: Programming Language :: Python :: 3.8
Classifier: Programming Language :: Python :: 3.9
Classifier: Programming Language :: Python :: 3.10
Classifier: Programming Language :: Python :: 3.11
Classifier: Programming Language :: Python :: 3.12
Classifier: Topic :: Software Development :: Documentation
Classifier: Topic :: Utilities
Requires-Python: >=3.7
License-File: LICENSE
Requires-Dist: flask>=2.0
Requires-Dist: flask-cors>=3.0
Provides-Extra: dev
Requires-Dist: pytest>=7.0; extra == "dev"
Requires-Dist: build; extra == "dev"
Requires-Dist: twine; extra == "dev"
Dynamic: license-file
